.DS_Store
PET_Dosage/PET_Dosage.py
PET_Dosage/PET_Dosage_Example_Use.py
PET_Dosage/PET_Dosage_Tests.py
PET_Dosage/__init__.py
PET_Dosage/test_PET_Dosage.py
PET_Dosage/testing_pip.py
PET_Dosage-0.0.3.dist-info/METADATA
PET_Dosage-0.0.3.dist-info/WHEEL
PET_Dosage-0.0.3.dist-info/top_level.txt
PET_Dosage-0.0.3.dist-info/RECORD
