Metadata-Version: 2.1
Name: PET-Dosage
Version: 0.0.3
Summary: Patient specific PET radiotracer dosage
Home-page: UNKNOWN
Author: fthirlwell (Florence Thirlwell)
Author-email: <florencethirlwell@gmail.com>
License: UNKNOWN
Keywords: python,PET Scan,dosage
Platform: UNKNOWN
Classifier: Development Status :: 1 - Planning
Classifier: Intended Audience :: Healthcare Industry
Classifier: Programming Language :: Python :: 3
Classifier: Operating System :: Unix
Classifier: Operating System :: MacOS :: MacOS X
Classifier: Operating System :: Microsoft :: Windows
